[{"id": "46f890010068369ea1614600597ab4e60e288e4aad8", "inputtime": "2022-01-12", "s2": "天津市高级人民法院", "s7": "（2021）津民终814号", "s11": "合同纠纷", "s41": "2022-05-09", "title": "中国民航大学、北京东瑞麒麟舞美文化有限公司等合同纠纷民事二审民事判决书", "username": "中国民航大学,北京东瑞麒麟舞美文化有限公司,北京世纪奥景文化传媒有限公司"}, {"id": "41f681993006019ce1a66033896434417a17785ff09", "inputtime": "2022-06-29", "s2": "天津市高级人民法院", "s7": "（2022）津刑申37号", "s11": "合同诈骗", "s41": "2022-07-05", "title": "张广义合同诈骗罪刑事申诉再审审查刑事通知书", "username": "张广义"}, {"id": "168c773990060f81e1a2be632b91b4fe5a5ea2ae134", "inputtime": "2022-04-28", "s2": "天津市高级人民法院", "s7": "（2022）津民抗7号", "s11": "商品房销售合同纠纷", "s41": "2022-05-08", "title": "朱士萍、天津国能房地产开发有限公司商品房销售合同纠纷民事抗诉再审审查民事裁定书", "username": "朱士萍,天津国能房地产开发有限公司"}, {"id": "98cc16839600110eb7ea03011b7da4af1e29bc78c75", "inputtime": "2022-03-30", "s2": "天津市高级人民法院", "s7": "（2022）津民抗4号", "s11": "案外人执行异议之诉", "s41": "2022-06-24", "title": "洪慧茹、中国银行股份有限公司天津河东支行等案外人执行异议之诉民事抗诉再审审查民事裁定书", "username": "洪慧茹,中国银行股份有限公司天津河东支行,孙鹏"}, {"id": "1680c53c900609d1e1a27673780e34f6dab8660be44", "inputtime": "2022-02-28", "s2": "天津市高级人民法院", "s7": "（2021）津民终1114号", "s11": "侵害作品信息网络传播权纠纷", "s41": "2022-07-21", "title": "深圳爱问科技股份有限公司、海南爱问众创科技有限公司等侵害作品信息网络传播权纠纷民事二审民事判决书", "username": "深圳爱问科技股份有限公司,海南爱问众创科技有限公司,北京新浪互联信息服务有限公司,中文在线数字出版集团股份有限公司东丽分公司"}, {"id": "31620398306117030a7ea70aeae9b4193cf11fdf416", "inputtime": "2022-03-04", "s2": "天津市高级人民法院", "s7": "（2021）津民申4170号", "s11": "机动车交通事故责任纠纷", "s41": "2022-04-17", "title": "任娜、郭金和等机动车交通事故责任纠纷民事申请再审审查民事裁定书", "username": "任娜,郭金和,中国平安财产保险股份有限公司天津市津南支公司"}, {"id": "933c90100698d3eafe61417378927424a69ccb44161", "inputtime": "2022-02-28", "s2": "天津市高级人民法院", "s7": "（2021）津民终1121号", "s11": "侵害作品信息网络传播权纠纷", "s41": "2022-07-21", "title": "深圳爱问科技股份有限公司、海南爱问众创科技有限公司等侵害作品信息网络传播权纠纷民事二审民事判决书", "username": "深圳爱问科技股份有限公司,海南爱问众创科技有限公司,北京新浪互联信息服务有限公司,中文在线数字出版集团股份有限公司东丽分公司"}, {"id": "686c9001096836dea13167a3785344a18646a4dd678", "inputtime": "2022-02-28", "s2": "天津市高级人民法院", "s7": "（2021）津民终1110号", "s11": "侵害作品信息网络传播权纠纷", "s41": "2022-07-21", "title": "深圳爱问科技股份有限公司、华著盛阅（天津）文化产业有限公司侵害作品信息网络传播权纠纷民事二审民事判决书", "username": "深圳爱问科技股份有限公司,华著盛阅（天津）文化产业有限公司"}, {"id": "7d0390100a768e3a61107a370898b42e89a2d3a0790", "inputtime": "2022-03-04", "s2": "天津市高级人民法院", "s7": "（2021）津民申4007号", "s11": "所有权确认纠纷", "s41": "2022-04-17", "title": "田文恒、田文全所有权确认纠纷民事申请再审审查民事裁定书", "username": "田文恒,田文全"}, {"id": "10e6c6890036019de1a7327f592234fa9b88de8d382", "inputtime": "2022-02-28", "s2": "天津市高级人民法院", "s7": "（2021）津民终1109号", "s11": "侵害作品信息网络传播权纠纷", "s41": "2022-07-21", "title": "深圳爱问科技股份有限公司、华著盛阅（天津）文化产业有限公司侵害作品信息网络传播权纠纷民事二审民事判决书", "username": "深圳爱问科技股份有限公司,华著盛阅（天津）文化产业有限公司"}, {"id": "ba3c168396001109d7ea3d4e782c944252d313ef345", "inputtime": "2022-02-28", "s2": "天津市高级人民法院", "s7": "（2021）津民终1119号", "s11": "侵害作品信息网络传播权纠纷", "s41": "2022-07-21", "title": "深圳爱问科技股份有限公司、海南爱问众创科技有限公司等侵害作品信息网络传播权纠纷民事二审民事判决书", "username": "深圳爱问科技股份有限公司,海南爱问众创科技有限公司,北京新浪互联信息服务有限公司,中文在线数字出版集团股份有限公司东丽分公司"}, {"id": "51649c983061170309dea7e2bb3264d0db3e5714576", "inputtime": "2022-02-28", "s2": "天津市高级人民法院", "s7": "（2021）津民终1099号", "s11": "侵害作品信息网络传播权纠纷", "s41": "2022-07-21", "title": "成都阅然科技有限公司、中文在线数字出版集团股份有限公司东丽分公司侵害作品信息网络传播权纠纷民事二审民事判决书", "username": "成都阅然科技有限公司,中文在线数字出版集团股份有限公司东丽分公司"}, {"id": "855c168396001109d7ea3047785e64cde7304949e05", "inputtime": "2022-02-28", "s2": "天津市高级人民法院", "s7": "（2021）津民终1115号", "s11": "侵害作品信息网络传播权纠纷", "s41": "2022-07-21", "title": "深圳爱问科技股份有限公司、海南爱问众创科技有限公司等侵害作品信息网络传播权纠纷民事二审民事判决书", "username": "深圳爱问科技股份有限公司,海南爱问众创科技有限公司,北京新浪互联信息服务有限公司,中文在线数字出版集团股份有限公司东丽分公司"}, {"id": "1716c6890036019de1a7357ba8a7841ba0571b0f912", "inputtime": "2022-02-28", "s2": "天津市高级人民法院", "s7": "（2021）津民终1112号", "s11": "侵害作品信息网络传播权纠纷", "s41": "2022-07-21", "title": "深圳爱问科技股份有限公司、华著盛阅（天津）文化产业有限公司侵害作品信息网络传播权纠纷民事二审民事判决书", "username": "深圳爱问科技股份有限公司,华著盛阅（天津）文化产业有限公司"}, {"id": "168af03790060a61e1aa5c908a6fb47c51b3250cb64", "inputtime": "2022-02-17", "s2": "天津市第一中级人民法院", "s7": "（2022）津01民终807号", "s11": "商品房销售合同纠纷", "s41": "2022-04-01", "title": "天津金河湾置业有限公司、张鹏卓商品房销售合同纠纷民事二审民事裁定书", "username": "天津金河湾置业有限公司,张鹏卓"}, {"id": "1e0b68b361190980009ceaabf9f174c976d195dd263", "inputtime": "2022-02-17", "s2": "天津市第一中级人民法院", "s7": "（2022）津01民终813号", "s11": "商品房销售合同纠纷", "s41": "2022-07-05", "title": "天津金河湾置业有限公司、张秀玉商品房销售合同纠纷民事二审民事裁定书", "username": "天津金河湾置业有限公司,张秀玉"}, {"id": "d16e29000d4e68a736c1919089ef84043b42f3287e7", "inputtime": "2022-02-17", "s2": "天津市第一中级人民法院", "s7": "（2021）津01民终10806号", "s11": "劳动争议", "s41": "2022-03-03", "title": "天津纳福和国际贸易有限公司、纪英劳动争议民事二审民事判决书", "username": "天津纳福和国际贸易有限公司,纪英"}, {"id": "81568179300601a6e1a990d9885a843ecece5a40049", "inputtime": "2022-02-17", "s2": "天津市第一中级人民法院", "s7": "（2022）津01民终799号", "s11": "商品房销售合同纠纷", "s41": "2022-04-01", "title": "天津金河湾置业有限公司、郭鹏商品房销售合同纠纷民事二审民事裁定书", "username": "天津金河湾置业有限公司,郭鹏"}, {"id": "9116870a300601a6e1a7909b8bdce4b8cc96db64a29", "inputtime": "2022-02-17", "s2": "天津市第一中级人民法院", "s7": "（2022）津01民终103号", "s11": "机动车交通事故责任纠纷", "s41": "2022-04-01", "title": "中国人寿财产保险股份有限公司天津市分公司、冯磊等机动车交通事故责任纠纷民事二审民事判决书", "username": "中国人寿财产保险股份有限公司天津市分公司,冯磊,刘宏杰"}, {"id": "b9f690100a668e3a611490081ac96427e9c63f576b0", "inputtime": "2022-02-17", "s2": "天津市第一中级人民法院", "s7": "（2022）津01民终800号", "s11": "商品房销售合同纠纷", "s41": "2022-04-01", "title": "天津金河湾置业有限公司、刘向楠商品房销售合同纠纷民事二审民事裁定书", "username": "天津金河湾置业有限公司,刘向楠"}, {"id": "1a09b6890036019ce1a903837b784443bfae8254682", "inputtime": "2022-02-17", "s2": "天津市第一中级人民法院", "s7": "（2022）津01民终781号", "s11": "商品房销售合同纠纷", "s41": "2022-07-05", "title": "天津金河湾置业有限公司、余向前商品房销售合同纠纷民事二审民事裁定书", "username": "天津金河湾置业有限公司,余向前"}, {"id": "063790010a68366ea1718900890594151584007f388", "inputtime": "2022-02-17", "s2": "天津市第一中级人民法院", "s7": "（2022）津01民终793号", "s11": "商品房销售合同纠纷", "s41": "2022-04-01", "title": "天津金河湾置业有限公司、范杰商品房销售合同纠纷民事二审民事裁定书", "username": "天津金河湾置业有限公司,范杰"}, {"id": "f1e51900086e68a63601b19089ed84551a02bae4f87", "inputtime": "2022-02-17", "s2": "天津市第一中级人民法院", "s7": "（2022）津01民终829号", "s11": "商品房销售合同纠纷", "s41": "2022-03-30", "title": "天津金河湾置业有限公司、胡佳丽商品房销售合同纠纷民事二审民事裁定书", "username": "天津金河湾置业有限公司,胡佳丽"}, {"id": "1118168a00360196e1a9098718ba846d14cd4bbfe12", "inputtime": "2022-02-17", "s2": "天津市第一中级人民法院", "s7": "（2022）津01民终812号", "s11": "商品房销售合同纠纷", "s41": "2022-03-31", "title": "天津金河湾置业有限公司、赵亚娟商品房销售合同纠纷民事二审民事裁定书", "username": "天津金河湾置业有限公司,赵亚娟"}, {"id": "ae0d9010068863eac46181916b4ba47214878f48ca1", "inputtime": "2022-02-15", "s2": "天津市第一中级人民法院", "s7": "（2022）津01民辖终54号", "s11": "", "s41": "2022-03-30", "title": "北京快手科技有限公司、申某等买卖合同纠纷民事管辖上诉管辖裁定书", "username": "北京快手科技有限公司,申某,王某"}, {"id": "168c5e30a0060961e1a648916b3d1448a206a4b88a4", "inputtime": "2022-02-15", "s2": "天津市第一中级人民法院", "s7": "（2022）津01民辖终55号", "s11": "", "s41": "2022-03-31", "title": "天津国美电器有限公司、天津锦丰盛泰科技集团有限公司建设工程施工合同纠纷民事管辖上诉管辖裁定书", "username": "天津国美电器有限公司,天津锦丰盛泰科技集团有限公司"}, {"id": "181d68236119196000d4ea563b6ee4a1665e75cae43", "inputtime": "2022-02-15", "s2": "天津市第一中级人民法院", "s7": "（2021）津01民终10381号", "s11": "劳动争议", "s41": "2022-03-03", "title": "天津和兴物业管理有限公司、何延杰劳动争议民事二审民事判决书", "username": "天津和兴物业管理有限公司,何延杰"}, {"id": "81b016839600110169ea1ca76aec44635c6298acdd5", "inputtime": "2022-02-15", "s2": "天津市第一中级人民法院", "s7": "（2022）津01民辖48号", "s11": "", "s41": "2022-03-23", "title": "陈龙、李彤离婚后财产纠纷民事指定管辖管辖裁定书", "username": "陈龙,李彤"}, {"id": "1a9f668a003601b6e1a9136608abe4728f5909a8d52", "inputtime": "2022-02-15", "s2": "天津市第一中级人民法院", "s7": "（2021）津01民终10532号", "s11": "劳务合同纠纷", "s41": "2022-04-02", "title": "郭文博、杨晓丹劳务合同纠纷民事二审民事裁定书", "username": "郭文博,杨晓丹"}, {"id": "1d2d16839600110869ea1cba6935c465e6a2f78ae05", "inputtime": "2022-02-15", "s2": "天津市第一中级人民法院", "s7": "（2022）津01民辖终64号", "s11": "", "s41": "2022-03-30", "title": "姚会永、北京快手科技有限公司等网络购物合同纠纷民事管辖上诉管辖裁定书", "username": "姚会永,北京快手科技有限公司,杭州次元岛科技有限公司"}, {"id": "4160059830611901026ea63ec9c454c34bf78014276", "inputtime": "2022-02-15", "s2": "天津市第一中级人民法院", "s7": "（2022）津01民辖终71号", "s11": "", "s41": "2022-03-24", "title": "秦皇岛顺凯达建筑材料有限公司、天津佳宇建筑材料有限公司加工合同纠纷民事管辖上诉管辖裁定书", "username": "秦皇岛顺凯达建筑材料有限公司,天津佳宇建筑材料有限公司"}, {"id": "f1b685d9300601a6e1aa91976b646468b4131f4e9b9", "inputtime": "2022-02-15", "s2": "天津市第一中级人民法院", "s7": "（2021）津01民终9616号", "s11": "保险纠纷", "s41": "2022-04-01", "title": "中国人民财产保险股份有限公司信阳市分公司、天津佳玺物流有限公司保险纠纷民事二审民事判决书", "username": "中国人民财产保险股份有限公司信阳市分公司,天津佳玺物流有限公司"}, {"id": "11efc9000a6e68a036c1219168170445b64a471b0d7", "inputtime": "2022-02-15", "s2": "天津市第一中级人民法院", "s7": "（2022）津01民辖终73号", "s11": "", "s41": "2022-04-01", "title": "季海燕、绫致时装（天津）有限公司劳动争议民事管辖上诉管辖裁定书", "username": "季海燕,绫致时装（天津）有限公司"}, {"id": "10ef685361191a6000a6eac5795d4479f3c376a9263", "inputtime": "2022-02-15", "s2": "天津市第一中级人民法院", "s7": "（2022）津01民辖终72号", "s11": "", "s41": "2022-04-01", "title": "中驰交通运输有限公司、天津市金聚海物流有限公司等合同纠纷民事管辖上诉管辖裁定书", "username": "中驰交通运输有限公司,天津市金聚海物流有限公司,渤海财产保险股份有限公司天津分公司滨海支公司"}, {"id": "14196833611939400055eab53b3a84962873986a213", "inputtime": "2022-01-26", "s2": "天津市第一中级人民法院", "s7": "（2021）津01执异327号", "s11": "借款合同纠纷", "s41": "2022-03-11", "title": "中国信达资产管理股份有限公司天津市分公司、中国建设银行股份有限公司天津北辰支行等借款合同纠纷执行异议执行裁定书", "username": "中国信达资产管理股份有限公司天津市分公司,中国建设银行股份有限公司天津北辰支行,天津市皇泰新型机电节能材料有限公司,天津助友重工机器设备制造有限公司,天津市荣泰新型复合材料有限公司,苗喜元,苗立元,苗文雨,吕文陆,张作泉,么立国,石民,曹承美,苗宝元"}, {"id": "21cb29000d4e68a136d1819348f8c4daa8310d989a7", "inputtime": "2022-01-25", "s2": "天津市第一中级人民法院", "s7": "（2021）津01民终10261号", "s11": "劳动争议", "s41": "2022-03-03", "title": "许鑫、天津大学劳动争议民事二审民事判决书", "username": "许鑫,天津大学"}, {"id": "913683e9300601a6e1a89311492f049d138c90a4549", "inputtime": "2022-01-24", "s2": "天津市第一中级人民法院", "s7": "（2021）津01民终9026号", "s11": "劳动争议", "s41": "2022-04-01", "title": "刘金榜、天津同兴通达机电设备有限公司劳动争议民事二审民事判决书", "username": "刘金榜,天津同兴通达机电设备有限公司"}, {"id": "7b1590010268366ea19129034ba88462d82a89b9b18", "inputtime": "2022-01-25", "s2": "天津市第一中级人民法院", "s7": "（2021）津01刑终669号", "s11": "侵占", "s41": "2022-03-24", "title": "天津华宜针织有限公司、韩振旭等刑事二审刑事裁定书", "username": "天津华宜针织有限公司,韩振旭,孙纪明,张洪海"}, {"id": "216f5098306119030c2ea403e8fc04ec1ba76a5b376", "inputtime": "2022-01-24", "s2": "天津市第一中级人民法院", "s7": "（2021）津01民终10567号", "s11": "机动车交通事故责任纠纷", "s41": "2022-01-29", "title": "中国平安财产保险股份有限公司天津市南开支公司、赵术增等机动车交通事故责任纠纷民事二审民事判决书", "username": "中国平安财产保险股份有限公司天津市南开支公司,赵术增,董树兰,杨彭飞"}, {"id": "e1a68bf8300601e2e1a593394bd464053aa9cc45069", "inputtime": "2022-01-24", "s2": "天津市第一中级人民法院", "s7": "（2021）津01民终10123号", "s11": "劳动争议", "s41": "2022-01-31", "title": "刘连旺、天津渤商大百商贸股份有限公司劳动争议民事二审民事判决书", "username": "刘连旺,天津渤商大百商贸股份有限公司"}, {"id": "b12319000d2e68a53671a1934b4c94d676bb424ea77", "inputtime": "2022-01-26", "s2": "天津市第一中级人民法院", "s7": "（2022）津01刑更1号", "s11": "受贿", "s41": "2022-01-30", "title": "穆祥怀受贿罪刑罚与执行变更审查刑事裁定书", "username": "穆祥怀"}, {"id": "81e68ec9300601a6e1af937b4865f469a14f1782279", "inputtime": "2022-01-24", "s2": "天津市第一中级人民法院", "s7": "（2022）津01民辖终12号", "s11": "", "s41": "2022-04-01", "title": "平安养老保险股份有限公司河南分公司、陈晓东养老保险待遇纠纷民事管辖上诉管辖裁定书", "username": "平安养老保险股份有限公司河南分公司,陈晓东"}, {"id": "41aef8000e2e68aa3631a193494ec40375ffc738057", "inputtime": "2022-01-26", "s2": "天津市第一中级人民法院", "s7": "（2022）津01刑更3号", "s11": "故意杀人", "s41": "2022-01-31", "title": "高浩庭故意杀人罪刑罚与执行变更审查刑事裁定书", "username": "高浩庭"}, {"id": "1687503090060e21e1a848934949b4aae66a2354944", "inputtime": "2022-01-26", "s2": "天津市第一中级人民法院", "s7": "（2021）津01民终9294号", "s11": "侵权责任纠纷", "s41": "2022-01-31", "title": "刘新叶、张世萍等侵权责任纠纷民事二审民事判决书", "username": "刘新叶,张世萍,刘峰,天津市红桥土地房屋征收有限公司"}, {"id": "ce31901008668e3a611f946358488478bae269d9570", "inputtime": "2022-03-09", "s2": "天津市第一中级人民法院", "s7": "（2022）津01民辖终138号", "s11": "", "s41": "2022-03-30", "title": "魏瑞江、邢立存买卖合同纠纷民事管辖上诉管辖裁定书", "username": "魏瑞江,邢立存"}, {"id": "c1686a98306119060a6ea33768aae434d0befb88646", "inputtime": "2022-03-09", "s2": "天津市第一中级人民法院", "s7": "（2022）津01民终323号", "s11": "劳动争议", "s41": "2022-04-01", "title": "法利莱装配式建筑（天津）有限公司、郭强劳动争议民事二审民事判决书", "username": "法利莱装配式建筑（天津）有限公司,郭强"}, {"id": "614116839600110869ea65683af214a47dc9d6fd8c5", "inputtime": "2022-03-09", "s2": "天津市第一中级人民法院", "s7": "（2022）津01民辖终139号", "s11": "", "s41": "2022-03-30", "title": "江苏南通二建集团有限公司、天津市兆俊建筑工程有限公司建设工程施工合同纠纷民事管辖上诉管辖裁定书", "username": "江苏南通二建集团有限公司,天津市兆俊建筑工程有限公司"}, {"id": "151d668a003601b6e1a96e3cfa9ae443ed182e5f772", "inputtime": "2022-03-09", "s2": "天津市第一中级人民法院", "s7": "（2021）津01民终10544号", "s11": "机动车交通事故责任纠纷", "s41": "2022-04-02", "title": "中国人寿财产保险股份有限公司天津市分公司、张金良等机动车交通事故责任纠纷民事二审民事判决书", "username": "中国人寿财产保险股份有限公司天津市分公司,张金良,李东"}, {"id": "ec1590010d68369ea1e139e6381c6427a2315373178", "inputtime": "2022-03-09", "s2": "天津市第一中级人民法院", "s7": "（2022）津01执复28号", "s11": "其他案由", "s41": "2022-05-22", "title": "高原、曹敬妹等其他案由执行复议执行裁定书", "username": "高原,曹敬妹,高子爱,天津华悦盛达实业有限公司,天津高通房地产发展有限公司"}, {"id": "51607c98306119060a6ea3dcd905145551ac8a0cdb6", "inputtime": "2022-03-09", "s2": "天津市第一中级人民法院", "s7": "（2021）津01民终10836号", "s11": "劳动争议", "s41": "2022-04-01", "title": "张雷、天津宏灏通达建材有限公司劳动争议民事二审民事判决书", "username": "张雷,天津宏灏通达建材有限公司"}]