[{"id": "1dbc1687203601a2e3a62731ab51d42c5664e9b39c2", "inputtime": "2022-01-07", "s2": "天津市第二中级人民法院", "s7": "（2021）津02民终9145号", "s11": "民间借贷纠纷", "s41": "2022-01-27", "title": "张守杰、张慧君等民间借贷纠纷民事二审民事判决书", "username": "张守杰,张慧君,刘宽"}, {"id": "817e16838600130926ea20443b8a342617e167bbb85", "inputtime": "2022-01-07", "s2": "天津市第二中级人民法院", "s7": "（2021）津02民终9766号", "s11": "民间借贷纠纷", "s41": "2022-01-26", "title": "成都律联信用管理有限公司、宋志鹏民间借贷纠纷民事二审民事裁定书", "username": "成都律联信用管理有限公司,宋志鹏"}, {"id": "33a172010a68362ea1e386523943d4606f537dcfa18", "inputtime": "2022-01-07", "s2": "天津市第二中级人民法院", "s7": "（2021）津02民终8660号", "s11": "商品房销售合同纠纷", "s41": "2022-01-27", "title": "李江涛、天津市天汇房地产开发有限公司商品房销售合同纠纷民事二审民事判决书", "username": "李江涛,天津市天汇房地产开发有限公司"}, {"id": "1fa168636136293000d6eafefa32149009ea81da2c3", "inputtime": "2022-01-07", "s2": "天津市第二中级人民法院", "s7": "（2021）津02民终8091号", "s11": "劳动争议", "s41": "2022-04-04", "title": "天津市汇福金盛商贸有限公司、杨健劳动争议民事二审民事判决书", "username": "天津市汇福金盛商贸有限公司,杨健"}, {"id": "b7f19010069843eaf661c362390f34373455b51c221", "inputtime": "2022-01-07", "s2": "天津市第二中级人民法院", "s7": "（2021）津02民终8119号", "s11": "民间借贷纠纷", "s41": "2022-02-27", "title": "张志文、卢雪等民间借贷纠纷民事二审民事判决书", "username": "张志文,卢雪,卢冰"}, {"id": "71e687e93006015ce3af620438a7246a5306e9e6439", "inputtime": "2022-01-07", "s2": "天津市第二中级人民法院", "s7": "（2021）津02破126号", "s11": "", "s41": "2022-07-01", "title": "南京临空国际贸易有限公司、瑞融源科技（天津）有限公司破产清算强制清算与破产裁定书", "username": "南京临空国际贸易有限公司,瑞融源科技（天津）有限公司"}, {"id": "09c89010069863eaaa6113623ab9f4373c8e3353691", "inputtime": "2022-01-07", "s2": "天津市第二中级人民法院", "s7": "（2021）津02民终10464号", "s11": "商品房预售合同纠纷", "s41": "2022-03-31", "title": "天津市华景房地产开发有限公司、梁俊贤商品房预售合同纠纷民事二审民事裁定书", "username": "天津市华景房地产开发有限公司,梁俊贤"}, {"id": "5e6e8010069823ea25619362390264a1a2f3ebfcf11", "inputtime": "2022-01-07", "s2": "天津市第二中级人民法院", "s7": "（2021）津02民终9765号", "s11": "民间借贷纠纷", "s41": "2022-01-26", "title": "成都律联信用管理有限公司、杜津民间借贷纠纷民事二审民事裁定书", "username": "成都律联信用管理有限公司,杜津"}, {"id": "5c359001036836aea1b386e59a14b438b710840de18", "inputtime": "2022-05-05", "s2": "天津市第二中级人民法院", "s7": "（2021）津02民终9643号", "s11": "房屋租赁合同纠纷", "s41": "2022-06-01", "title": "刘昭明、天津科诚房地产开发有限公司等房屋租赁合同纠纷民事二审民事裁定书", "username": "刘昭明,天津科诚房地产开发有限公司,邢纪惠"}, {"id": "b16975983061360503aea955ebf3b486eb817ce14f6", "inputtime": "2022-05-05", "s2": "天津市第二中级人民法院", "s7": "（2022）津02民终663号", "s11": "商品房销售合同纠纷", "s41": "2022-06-01", "title": "天津博雅置业有限公司、贾利宇商品房销售合同纠纷民事二审民事判决书", "username": "天津博雅置业有限公司,贾利宇"}, {"id": "0d29168396001308a6ea51cd9b9e04e13d70b45b8b5", "inputtime": "2022-05-05", "s2": "天津市第二中级人民法院", "s7": "（2022）津02民终851号", "s11": "民间借贷纠纷", "s41": "2022-06-02", "title": "张宝清、王永鑫民间借贷纠纷民事二审民事判决书", "username": "张宝清,王永鑫"}, {"id": "5075168396001303a6ea55b59b65b4542c0cd61b805", "inputtime": "2022-05-05", "s2": "天津市第二中级人民法院", "s7": "（2022）津02民终616号", "s11": "财产损害赔偿纠纷", "s41": "2022-06-01", "title": "中铁建物业管理有限公司、中铁建物业管理有限公司天津分公司等财产损害赔偿纠纷民事二审民事判决书", "username": "中铁建物业管理有限公司,中铁建物业管理有限公司天津分公司,许静,中铁房地产集团商业地产开发管理有限公司"}, {"id": "d4e6901001a68e3a613e6959c9ea448ef9bcc19b9a0", "inputtime": "2022-05-05", "s2": "天津市第二中级人民法院", "s7": "（2022）津02民终1688号", "s11": "小额借款合同纠纷", "s41": "2022-05-26", "title": "天津华北创业小额贷款有限公司、陈振宇等小额借款合同纠纷民事二审民事判决书", "username": "天津华北创业小额贷款有限公司,陈振宇,王为平"}, {"id": "1180684361365a9000faeadde91b64e6b6127632383", "inputtime": "2022-05-05", "s2": "天津市第二中级人民法院", "s7": "（2022）津02民终648号", "s11": "股权转让纠纷", "s41": "2022-06-09", "title": "杨静、李兴股权转让纠纷民事二审民事判决书", "username": "杨静,李兴"}, {"id": "d2399001086836aea15356d59a906452e9c20ee8a18", "inputtime": "2022-05-05", "s2": "天津市第二中级人民法院", "s7": "（2022）津02民终869号", "s11": "民间借贷纠纷", "s41": "2022-06-02", "title": "王健、阳信县建丰房地产开发有限公司民间借贷纠纷民事二审民事判决书", "username": "王健,阳信县建丰房地产开发有限公司"}, {"id": "104296890036018ae3a65494ab23b41d2438f6bf9c2", "inputtime": "2022-05-05", "s2": "天津市第二中级人民法院", "s7": "（2022）津02民终600号", "s11": "买卖合同纠纷", "s41": "2022-06-02", "title": "张里平、赵书清等买卖合同纠纷民事二审民事判决书", "username": "张里平,赵书清,天津久昌博宇科技有限公司,天津市明彩印刷科技有限公司,杨丽丽,邹锋军"}, {"id": "5f7590100638a3ead46163659b2bc4211a36fc0d2b1", "inputtime": "2022-05-05", "s2": "天津市第二中级人民法院", "s7": "（2022）津02民终613号", "s11": "买卖合同纠纷", "s41": "2022-06-01", "title": "天津市沐阳纸业贸易有限公司、黄阿凤买卖合同纠纷民事二审民事判决书", "username": "天津市沐阳纸业贸易有限公司,黄阿凤"}, {"id": "b1bf690001ae68a536015365997724ba19c17bb55b7", "inputtime": "2022-05-05", "s2": "天津市第二中级人民法院", "s7": "（2022）津02民终3066号", "s11": "", "s41": "2022-05-26", "title": "刘四祥民事二审民事裁定书", "username": "刘四祥"}, {"id": "17867689003601e8e3a6774e295f54de8beb84b2b52", "inputtime": "2022-04-08", "s2": "天津市第二中级人民法院", "s7": "（2022）津02民终1905号", "s11": "机动车交通事故责任纠纷", "s41": "2022-05-07", "title": "渤海财产保险股份有限公司天津分公司、杨滨等机动车交通事故责任纠纷民事二审民事判决书", "username": "渤海财产保险股份有限公司天津分公司,杨滨,李鹏"}, {"id": "c72e901008868e3a61326774b80b14e2941b3bbb3c0", "inputtime": "2022-04-08", "s2": "天津市第二中级人民法院", "s7": "（2022）津02民终837号", "s11": "民间借贷纠纷", "s41": "2022-05-01", "title": "王若乔、王才厚等民间借贷纠纷民事二审民事裁定书", "username": "王若乔,王才厚,原鹏宇,天津来良建筑装修工程有限公司"}, {"id": "086816839600130696ea7dc54bd59455ac7cb027f55", "inputtime": "2022-04-08", "s2": "天津市第二中级人民法院", "s7": "（2022）津02民终2131号", "s11": "财产损害赔偿纠纷", "s41": "2022-05-15", "title": "崔洋洋民事二审民事裁定书", "username": "崔洋洋"}, {"id": "b607901000868e3a6137687429bcb4f0bcc20ecc530", "inputtime": "2022-04-08", "s2": "天津市第二中级人民法院", "s7": "（2022）津02执异54号", "s11": "其他案由", "s41": "2022-04-23", "title": "天津市辰昱投资管理有限公司、天津市油脂（集团）有限公司等其他案由执行异议执行裁定书", "username": "天津市辰昱投资管理有限公司,天津市油脂（集团）有限公司,天津市粮油集团有限公司"}, {"id": "3e6816839600130696ea7ecd487b84d509140b78615", "inputtime": "2022-04-08", "s2": "天津市第二中级人民法院", "s7": "（2022）津02民终2518号", "s11": "教育培训合同纠纷", "s41": "2022-05-15", "title": "张玉珍、马健等教育培训合同纠纷民事二审民事裁定书", "username": "张玉珍,马健,刘某,天津优能力胜未来培训学校有限公司第六分公司,天津优能力胜未来培训学校有限公司"}, {"id": "5ce690010a68369ea18396274b3d5469f44d9075638", "inputtime": "2022-04-08", "s2": "天津市第二中级人民法院", "s7": "（2022）津02民终913号", "s11": "劳动合同纠纷", "s41": "2022-05-19", "title": "胡广玲、天津市津南区鸿泰乐尔之家老年公寓劳动合同纠纷民事二审民事判决书", "username": "胡广玲,天津市津南区鸿泰乐尔之家老年公寓"}, {"id": "ae5890010668369ea1c3868748e0d4ad57190a9c068", "inputtime": "2022-04-08", "s2": "天津市第二中级人民法院", "s7": "（2022）津02民终740号", "s11": "所有权确认纠纷", "s41": "2022-05-15", "title": "天津市北辰区北仓镇王秦庄村民委员会、天津市规划和自然资源局北辰分局等所有权确认纠纷民事二审民事判决书", "username": "天津市北辰区北仓镇王秦庄村民委员会,天津市规划和自然资源局北辰分局,天津市金发市政工程有限公司"}, {"id": "633f16839600130886ea79eb4a2b8450f69fb072da5", "inputtime": "2022-04-08", "s2": "天津市第二中级人民法院", "s7": "（2021）津02民终9113号", "s11": "企业出资人权益确认纠纷", "s41": "2022-05-01", "title": "齐凤山、天津现代脾胃病医院等企业出资人权益确认纠纷民事二审民事判决书", "username": "齐凤山,天津现代脾胃病医院,庞树玲,庞树英,庞树霞,庞树梅"}, {"id": "f161789830613607069ea4bc89cd046d8a82fcad236", "inputtime": "2022-04-08", "s2": "天津市第二中级人民法院", "s7": "（2022）津02民特71号", "s11": "申请撤销仲裁裁决", "s41": "2022-05-15", "title": "天津市发电技术设备有限公司、齐燕青申请撤销仲裁裁决撤销仲裁裁决民事裁定书", "username": "天津市发电技术设备有限公司,齐燕青"}, {"id": "a162a99830613607078ea4c22976f43ee0eb49fce26", "inputtime": "2022-04-08", "s2": "天津市第二中级人民法院", "s7": "（2022）津02民终1288号", "s11": "合同纠纷", "s41": "2022-04-30", "title": "何东升、温慧静等合同纠纷民事二审民事判决书", "username": "何东升,温慧静,王鸣"}, {"id": "5118990008ae68a43691f37059b9d4d2d9afc3f2b47", "inputtime": "2022-04-25", "s2": "天津市第二中级人民法院", "s7": "（2022）津02民终1747号", "s11": "买卖合同纠纷", "s41": "2022-06-02", "title": "天津二建建筑工程有限公司、天津恒通瑞祥电气设备制造有限公司等买卖合同纠纷民事二审民事判决书", "username": "天津二建建筑工程有限公司,天津恒通瑞祥电气设备制造有限公司,天津渔阳建工集团有限公司"}, {"id": "d1ad690000be68ad36917370584814ce7799c513187", "inputtime": "2022-04-25", "s2": "天津市第二中级人民法院", "s7": "（2022）津02民辖终107号", "s11": "", "s41": "2022-06-10", "title": "天津市裕丰石化设备安装有限公司、天津市滨海新区古林街道工农村村民委员会等民间借贷纠纷民事管辖上诉管辖裁定书", "username": "天津市裕丰石化设备安装有限公司,天津市滨海新区古林街道工农村村民委员会,天津滨海新区大港英捷纸制品厂,李育珊"}, {"id": "51688d983061370003cea561fbcc745f80814f3b026", "inputtime": "2022-04-25", "s2": "天津市第二中级人民法院", "s7": "（2022）津02民辖109号", "s11": "", "s41": "2022-06-29", "title": "天津佳智德商贸有限公司、清源光电（天津）有限公司买卖合同纠纷民事指定管辖管辖裁定书", "username": "天津佳智德商贸有限公司,清源光电（天津）有限公司"}, {"id": "1688283e90060881e3aedb70593934ac2df78dfd474", "inputtime": "2022-04-25", "s2": "天津市第二中级人民法院", "s7": "（2022）津02执异123号", "s11": "合同纠纷", "s41": "2022-05-01", "title": "上海浦东发展银行股份有限公司天津分行、重庆易极付科技有限公司等合同纠纷执行异议执行裁定书", "username": "上海浦东发展银行股份有限公司天津分行,重庆易极付科技有限公司,重庆市博恩科技（集团）有限公司,吴琪,刘强,熊新翔,琼海博鳌幸福联盟投资有限公司,重庆汇涌金股权投资基金管理有限公司"}, {"id": "126d96890036018ae3a70e5718bd9432c5c71c19852", "inputtime": "2022-04-25", "s2": "天津市第二中级人民法院", "s7": "（2022）津02民初615号", "s11": "劳动争议", "s41": "2022-06-02", "title": "王某某、天津铁厂有限公司劳动争议民事一审民事裁定书", "username": "王某某,天津铁厂有限公司"}, {"id": "1dda56890036013ae3a702516ba974d8ea985666d22", "inputtime": "2022-04-25", "s2": "天津市第二中级人民法院", "s7": "（2022）津02民终1729号", "s11": "房屋租赁合同纠纷", "s41": "2022-06-01", "title": "李伶、天津渤海置业有限公司等房屋租赁合同纠纷民事二审民事判决书", "username": "李伶,天津渤海置业有限公司,天津艾美亨美容有限公司"}, {"id": "91614898306137000fdea5093baeb438316abb9c536", "inputtime": "2022-04-25", "s2": "天津市第二中级人民法院", "s7": "（2022）津02民终589号", "s11": "买卖合同纠纷", "s41": "2022-07-27", "title": "周建军、天津市文达电缆轴有限公司买卖合同纠纷民事二审民事判决书", "username": "周建军,天津市文达电缆轴有限公司"}, {"id": "d68e901008868e3a61307805894324b106ccd540650", "inputtime": "2022-04-25", "s2": "天津市第二中级人民法院", "s7": "（2022）津02执异129号", "s11": "合同纠纷", "s41": "2022-05-01", "title": "上海浦东发展银行股份有限公司天津分行、重庆易极付科技有限公司等合同纠纷执行异议执行裁定书", "username": "上海浦东发展银行股份有限公司天津分行,重庆易极付科技有限公司,重庆市博恩科技（集团）有限公司,吴琪,刘强,熊新翔,琼海博鳌幸福联盟投资有限公司,郭玉琼"}, {"id": "0ff4a01006f8a3ea576163705bbca4b52eb246be201", "inputtime": "2022-04-25", "s2": "天津市第二中级人民法院", "s7": "（2022）津02民终2571号", "s11": "合同纠纷", "s41": "2022-06-09", "title": "天津亚星世纪实业股份有限公司、天津市全拓物流有限公司合同纠纷民事二审民事裁定书", "username": "天津亚星世纪实业股份有限公司,天津市全拓物流有限公司"}, {"id": "1116836a300601fae3a070d258b22489f17d58c0f69", "inputtime": "2022-04-25", "s2": "天津市第二中级人民法院", "s7": "（2022）津02民辖终130号", "s11": "", "s41": "2022-06-09", "title": "天津市鑫通旺达建筑劳务服务有限公司、天津市广盛建筑器材租赁站建筑设备租赁合同纠纷民事管辖上诉管辖裁定书", "username": "天津市鑫通旺达建筑劳务服务有限公司,天津市广盛建筑器材租赁站"}, {"id": "1689e33490060c61e3a7f6717a86f4b5ce37ab2e6a4", "inputtime": "2022-03-23", "s2": "天津市第二中级人民法院", "s7": "（2022）津02民终2115号", "s11": "旅游合同纠纷", "s41": "2022-04-03", "title": "阎冲、郝如连等旅游合同纠纷民事二审民事裁定书", "username": "阎冲,郝如连,天津市红牛国际旅行社有限公司"}, {"id": "1489901008868e3a61387a17ab69c46881f3e560a90", "inputtime": "2022-03-23", "s2": "天津市第二中级人民法院", "s7": "（2022）津02民终271号", "s11": "买卖合同纠纷", "s41": "2022-05-01", "title": "田国兴、韩文福等买卖合同纠纷民事二审民事判决书", "username": "田国兴,韩文福,郑成山,郑琳琳"}, {"id": "11354689003601c6e3a71a778b78042542202f41e42", "inputtime": "2022-03-23", "s2": "天津市第二中级人民法院", "s7": "（2022）津02民终2096号", "s11": "机动车交通事故责任纠纷", "s41": "2022-04-03", "title": "太平财产保险有限公司天津分公司津东支公司、宋景龙等机动车交通事故责任纠纷民事二审民事判决书", "username": "太平财产保险有限公司天津分公司津东支公司,宋景龙,张金仲,中国平安财产保险股份有限公司天津分公司,天津市道路交通事故社会救助基金管理办公室"}, {"id": "71606498306137010c6ea7193823a474a1b7ed09d46", "inputtime": "2022-03-23", "s2": "天津市第二中级人民法院", "s7": "（2022）津02民辖终77号", "s11": "", "s41": "2022-04-03", "title": "香河运博工程技术有限公司、许帅等买卖合同纠纷民事管辖上诉管辖裁定书", "username": "香河运博工程技术有限公司,许帅,天津市北辰区奥通佳业建材销售中心"}, {"id": "b114990005ce68a336e1f3717b7db4692c8471f4f67", "inputtime": "2022-03-23", "s2": "天津市第二中级人民法院", "s7": "（2021）津02破申208号", "s11": "", "s41": "2022-07-01", "title": "天津市久跃科技有限公司、天津华泰汽车车身制造有限公司破产申请审查强制清算与破产裁定书", "username": "天津市久跃科技有限公司,天津华泰汽车车身制造有限公司"}, {"id": "cd38901000968e3a61377717eb4df473c3498c0f920", "inputtime": "2022-03-23", "s2": "天津市第二中级人民法院", "s7": "（2021）津02民初911号", "s11": "侵害商标权纠纷", "s41": "2022-05-09", "title": "山东金号家纺集团有限公司、天津市津南区美佳宜购副食店侵害商标权纠纷民事一审民事判决书", "username": "山东金号家纺集团有限公司,天津市津南区美佳宜购副食店"}, {"id": "764490100c668e3a61317017aac7b4c2f1da09cf890", "inputtime": "2022-03-23", "s2": "天津市第二中级人民法院", "s7": "（2022）津02民终2113号", "s11": "农村房屋买卖合同纠纷", "s41": "2022-04-03", "title": "张振廷、郑学云等农村房屋买卖合同纠纷民事二审民事裁定书", "username": "张振廷,郑学云,王玉红,张振利,于建双"}, {"id": "11754689003601c6e3a71072ebe5c40e9a69e2e5342", "inputtime": "2022-03-23", "s2": "天津市第二中级人民法院", "s7": "（2022）津02民终1764号", "s11": "买卖合同纠纷", "s41": "2022-04-03", "title": "保定众智模具制造有限公司、天津博恒鑫金属材料贸易有限公司买卖合同纠纷民事二审民事判决书", "username": "保定众智模具制造有限公司,天津博恒鑫金属材料贸易有限公司"}, {"id": "b4b1a0100b668e3a61347117c890248031b825b0980", "inputtime": "2022-03-23", "s2": "天津市第二中级人民法院", "s7": "（2021）津02民终10322号", "s11": "民间借贷纠纷", "s41": "2022-04-02", "title": "李培、徐峰民间借贷纠纷民事二审民事判决书", "username": "李培,徐峰"}, {"id": "3166f99830613701088ea73debab44c273deee5b826", "inputtime": "2022-03-23", "s2": "天津市第二中级人民法院", "s7": "（2022）津02民终248号", "s11": "合同纠纷", "s41": "2022-05-01", "title": "天津市创维机械设备制造有限公司、天津市天发重型水电设备制造有限公司合同纠纷民事二审民事判决书", "username": "天津市创维机械设备制造有限公司,天津市天发重型水电设备制造有限公司"}, {"id": "7523901006b873eaac61f372590ab450eece669ef61", "inputtime": "2022-04-06", "s2": "天津市第二中级人民法院", "s7": "（2021）津02民终9824号", "s11": "返还原物纠纷", "s41": "2022-04-18", "title": "徐甲炯、郭秀琪返还原物纠纷民事二审民事判决书", "username": "徐甲炯,郭秀琪"}, {"id": "16808537900600b1e3a1f2725a044443a8bb8dc3964", "inputtime": "2022-04-06", "s2": "天津市第二中级人民法院", "s7": "（2022）津02民申12号", "s11": "买卖合同纠纷", "s41": "2022-06-10", "title": "杨国际、张强买卖合同纠纷民事申请再审审查民事裁定书", "username": "杨国际,张强"}]